gera2ld/pyserve/__init__.py
gera2ld/pyserve/host.py
gera2ld_pyserve-0.3.2.dist-info/METADATA
gera2ld_pyserve-0.3.2.dist-info/WHEEL
gera2ld_pyserve-0.3.2.dist-info/RECORD
