Metadata-Version: 2.4
Name: gera2ld-pyserve
Version: 0.3.2
Summary: Start serving an asyncio.Server
License: MIT
Author: Gerald
Author-email: gera2ld@163.com
Requires-Python: >=3.6,<4.0
Classifier: License :: OSI Approved :: MIT License
Classifier: Programming Language :: Python :: 3
Classifier: Programming Language :: Python :: 3.6
Classifier: Programming Language :: Python :: 3.7
Classifier: Programming Language :: Python :: 3.8
Classifier: Programming Language :: Python :: 3.9
Classifier: Programming Language :: Python :: 3.10
Classifier: Programming Language :: Python :: 3.11
Classifier: Programming Language :: Python :: 3.12
Classifier: Programming Language :: Python :: 3.13
Classifier: Programming Language :: Python :: 3.14
Provides-Extra: aio
Requires-Dist: aiohttp (>=3.6.2,<4.0.0) ; extra == "aio"
Project-URL: Repository, https://github.com/gera2ld/pyserve
